TesultsListener.py
robot_tesults-1.2.0.dist-info/LICENSE
robot_tesults-1.2.0.dist-info/METADATA
robot_tesults-1.2.0.dist-info/WHEEL
robot_tesults-1.2.0.dist-info/entry_points.txt
robot_tesults-1.2.0.dist-info/top_level.txt
robot_tesults-1.2.0.dist-info/RECORD
